setup.py
distributions_nim/Binomialdistribution.py
distributions_nim/Gaussiandistribution.py
distributions_nim/Generaldistribution.py
distributions_nim/__init__.py
distributions_nim.egg-info/PKG-INFO
distributions_nim.egg-info/SOURCES.txt
distributions_nim.egg-info/dependency_links.txt
distributions_nim.egg-info/not-zip-safe
distributions_nim.egg-info/top_level.txt